piasync/__init__.py
piasync/dbus.py
piasync/pia.py
piasync-0.10.dist-info/METADATA
piasync-0.10.dist-info/WHEEL
piasync-0.10.dist-info/entry_points.txt
piasync-0.10.dist-info/top_level.txt
piasync-0.10.dist-info/RECORD
