Metadata-Version: 2.1
Name: piasync
Version: 0.10
Summary: Maintains Network Manager connections for the Private Internet Access VPN servers
Home-page: https://github.com/mattboyer/piasync
Author: Matt Boyer
Author-email: mboyer@sdf.org
License: BSD
Platform: UNKNOWN
Classifier: Environment :: Console
Classifier: Development Status :: 2 - Pre-Alpha
Classifier: Intended Audience :: Developers
Classifier: License :: OSI Approved :: BSD License
Classifier: Operating System :: POSIX
Classifier: Programming Language :: Python :: 3
Requires-Dist: countrynames
Requires-Dist: jeepney
Requires-Dist: requests
